Metadata-Version: 2.1
Name: easy-kmer
Version: 1.0
Summary: A library for working with k-mers in bioinformatics
Home-page: https://github.com/shosuke13/kmer
Author: Shosuke Suzuki
License: UNKNOWN
Platform: UNKNOWN
